{"root":[{"assemblyName":"ACTk.Runtime","nameSpace":"CodeStage.AntiCheat.Storage","className":"ObscuredFilePrefs","methodName":"RegisterQuitDetection","loadTypes":0,"isUnityClass":false},{"assemblyName":"ACTk.Runtime","nameSpace":"CodeStage.AntiCheat.Common","className":"ACTk","methodName":"GetUnityInfo","loadTypes":0,"isUnityClass":false},{"assemblyName":"Cinemachine","nameSpace":"Cinemachine","className":"CinemachineStoryboard","methodName":"InitializeModule","loadTypes":0,"isUnityClass":false},{"assemblyName":"Cinemachine","nameSpace":"Cinemachine","className":"CinemachineCore","methodName":"InitializeModule","loadTypes":0,"isUnityClass":false},{"assemblyName":"Cinemachine","nameSpace":"Cinemachine","className":"UpdateTracker","methodName":"InitializeModule","loadTypes":0,"isUnityClass":false},{"assemblyName":"Cinemachine","nameSpace":"Cinemachine","className":"CinemachineImpulseManager","methodName":"InitializeModule","loadTypes":0,"isUnityClass":false},{"assemblyName":"Cinemachine","nameSpace":"Cinemachine.PostFX","className":"CinemachinePostProcessing","methodName":"InitializeModule","loadTypes":0,"isUnityClass":false}]}
